arcade_xero_api/__init__.py
arcade_xero_api/moar/Xero.json
arcade_xero_api/moar/openapi.json
arcade_xero_api/tools/__init__.py
arcade_xero_api/tools/request_body_schemas.py
arcade_xero_api/wrapper_tools/AddContactHistoryRecord.json
arcade_xero_api/wrapper_tools/AddExpenseClaimHistory.json
arcade_xero_api/wrapper_tools/AddQuoteHistory.json
arcade_xero_api/wrapper_tools/CreateBankTransactionHistory.json
arcade_xero_api/wrapper_tools/CreateBankTransferHistory.json
arcade_xero_api/wrapper_tools/CreateBatchPaymentHistoryRecord.json
arcade_xero_api/wrapper_tools/CreateInvoiceHistory.json
arcade_xero_api/wrapper_tools/CreateItemHistory.json
arcade_xero_api/wrapper_tools/CreateJournalHistoryRecord.json
arcade_xero_api/wrapper_tools/CreatePaymentHistoryRecord.json
arcade_xero_api/wrapper_tools/CreatePrepaymentHistory.json
arcade_xero_api/wrapper_tools/CreatePurchaseOrderHistory.json
arcade_xero_api/wrapper_tools/CreateRepeatingInvoiceHistory.json
arcade_xero_api/wrapper_tools/DeleteAccount.json
arcade_xero_api/wrapper_tools/DeleteCreditNoteAllocation.json
arcade_xero_api/wrapper_tools/DeleteInventoryItem.json
arcade_xero_api/wrapper_tools/DeleteLinkedTransaction.json
arcade_xero_api/wrapper_tools/DeleteOverpaymentAllocation.json
arcade_xero_api/wrapper_tools/DeletePrepaymentAllocation.json
arcade_xero_api/wrapper_tools/DeleteTrackingOption.json
arcade_xero_api/wrapper_tools/FetchAllXeroContacts.json
arcade_xero_api/wrapper_tools/FetchBankTransferAttachment.json
arcade_xero_api/wrapper_tools/FetchCreditNoteHistory.json
arcade_xero_api/wrapper_tools/FetchInvoicePayments.json
arcade_xero_api/wrapper_tools/FetchPurchaseOrderAttachment.json
arcade_xero_api/wrapper_tools/GetAgedPayablesReportByContact.json
arcade_xero_api/wrapper_tools/GetAgedReceivablesReportByContact.json
arcade_xero_api/wrapper_tools/GetBalanceSheetReport.json
arcade_xero_api/wrapper_tools/GetBankSummaryReport.json
arcade_xero_api/wrapper_tools/GetBankTransactionAttachment.json
arcade_xero_api-2.0.0.dist-info/METADATA
arcade_xero_api-2.0.0.dist-info/WHEEL
arcade_xero_api-2.0.0.dist-info/entry_points.txt
arcade_xero_api-2.0.0.dist-info/licenses/LICENSE
arcade_xero_api-2.0.0.dist-info/RECORD
